odoo/addons/website_typed_text/README.rst
odoo/addons/website_typed_text/__init__.py
odoo/addons/website_typed_text/__manifest__.py
odoo/addons/website_typed_text/i18n/ca.po
odoo/addons/website_typed_text/i18n/es.po
odoo/addons/website_typed_text/i18n/website_typed_text.pot
odoo/addons/website_typed_text/readme/CONTRIBUTORS.rst
odoo/addons/website_typed_text/readme/DESCRIPTION.rst
odoo/addons/website_typed_text/readme/USAGE.rst
odoo/addons/website_typed_text/static/description/demo.gif
odoo/addons/website_typed_text/static/description/icon.png
odoo/addons/website_typed_text/static/description/index.html
odoo/addons/website_typed_text/static/lib/typedjs/LICENSE.txt
odoo/addons/website_typed_text/static/lib/typedjs/typed.js
odoo/addons/website_typed_text/static/src/js/editor.js
odoo/addons/website_typed_text/static/src/js/frontend.js
odoo/addons/website_typed_text/static/src/xml/editor.xml
odoo/addons/website_typed_text/templates/assets.xml
odoo/addons/website_typed_text/templates/snippets.xml
odoo13_addon_website_typed_text-13.0.1.0.1.dist-info/METADATA
odoo13_addon_website_typed_text-13.0.1.0.1.dist-info/WHEEL
odoo13_addon_website_typed_text-13.0.1.0.1.dist-info/top_level.txt
odoo13_addon_website_typed_text-13.0.1.0.1.dist-info/RECORD
